genetic_algorithm_py/__init__.py
genetic_algorithm_py/algorithm.py
genetic_algorithm_py/individual.py
genetic_algorithm_py/population.py
genetic_algorithm_py/defaults/__init__.py
genetic_algorithm_py/defaults/crossover.py
genetic_algorithm_py/defaults/fitness_function.py
genetic_algorithm_py/defaults/mutation.py
genetic_algorithm_py/defaults/selection.py
genetic_algorithm_py/strategy/__init__.py
genetic_algorithm_py/strategy/crossover_strategy.py
genetic_algorithm_py/strategy/dna_strategy.py
genetic_algorithm_py/strategy/fitness_strategy.py
genetic_algorithm_py/strategy/mutation_strategy.py
genetic_algorithm_py/strategy/selection_strategy.py
genetic_algorithm_py-1.0.1.dist-info/LICENSE
genetic_algorithm_py-1.0.1.dist-info/METADATA
genetic_algorithm_py-1.0.1.dist-info/WHEEL
genetic_algorithm_py-1.0.1.dist-info/top_level.txt
genetic_algorithm_py-1.0.1.dist-info/RECORD
