Metadata-Version: 2.1
Name: genetic-algorithm-py
Version: 1.0.1
Summary: A genetic algorithm library for solving optimization problems
Home-page: https://github.com/MrHardik-k/genetic-algorithm
Author: Kanzariya Hardik
Author-email: hardikkanzariya091@gmail.com
License: UNKNOWN
Platform: UNKNOWN
Classifier: Programming Language :: Python :: 3
Classifier: License :: OSI Approved :: MIT License
Classifier: Operating System :: OS Independent
Requires-Python: >=3.6
License-File: LICENSE
